mela/__init__.py
mela/abc.py
mela/exceptions.py
mela/log.py
mela/processor.py
mela/components/__init__.py
mela/components/base.py
mela/components/consumer.py
mela/components/exceptions.py
mela/components/publisher.py
mela/components/rpc.py
mela/components/service.py
mela/factories/__init__.py
mela/factories/consumer.py
mela/factories/publisher.py
mela/factories/rpc.py
mela/factories/service.py
mela/factories/core/__init__.py
mela/factories/core/connection.py
mela/factories/core/exchange.py
mela/factories/core/queue.py
mela/scheme/__init__.py
mela/scheme/requirement.py
mela/settings/__init__.py
mela-1.1.1.dist-info/LICENSE
mela-1.1.1.dist-info/METADATA
mela-1.1.1.dist-info/WHEEL
mela-1.1.1.dist-info/top_level.txt
mela-1.1.1.dist-info/RECORD
