Metadata-Version: 2.1
Name: mela
Version: 1.1.1
Summary: Let's make microservice development fun again!
Home-page: https://github.com/alem-research/mela
Author: Daniyar Supiyev
Author-email: undead.thunderbird@gmail.com
Classifier: Programming Language :: Python :: 3
Classifier: License :: OSI Approved :: Apache Software License
Classifier: Operating System :: OS Independent
Classifier: Development Status :: 4 - Beta
Classifier: Framework :: AsyncIO
Classifier: Topic :: Software Development :: Libraries :: Application Frameworks
Classifier: 
Requires-Python: >=3.11
License-File: LICENSE
Requires-Dist: aio-pika (==9.0.7)
Requires-Dist: envyaml (==1.10.211231)
Requires-Dist: anyio (==3.6.2)
Requires-Dist: pydantic (==1.10.7)
